verilog/Multiplier_8x8.v
`include "verilog/Adder.v"
module Carry_Look_Ahead_Adder
        (   input [4:0] A,B,
            output [4:0] S
            );
            
    wire [4:0] P;
    wire [3:0] G;
    wire [3:0] C;   
    
        //first level
    assign P = A ^ B;
    assign G = A[3:0] & B[3:0];

    //second level
    // assign C[0] = cin;
    assign C[0] = G[0];
    assign C[1] = G[1] | (P[1] & G[0]) ;
    assign C[2] = G[2] | (P[2] & G[1]) | (P[2] & P[1] & G[0]);
    assign C[3] = G[3] | (P[3] & G[2]) | (P[3] & P[2] & G[1]) | 
            (P[3] & P[2] & P[1] & G[0]);

    //third level
    assign S[0] = P[0];
    assign S[4:1] = P[4:1] ^ C[3:0];

endmodule
module M4_Carry_Look_Ahead_Adder (
    output [4:0]  S,
    input  [4:0] A,
    input  [3:0] B
    );
    wire [4:0] P;
    wire [3:0] G;
    wire [3:0] C;   
    
    //first level
    assign P[4] =A[4];
    assign P[3:0] = A[3:0] ^ B;
    assign G = A[3:0] & B;

    //second level
    assign C[0] = G[0];
    assign C[1] = G[1] | (P[1] & G[0]) ;
    assign C[2] = G[2] | (P[2] & G[1]) | (P[2] & P[1] & G[0]);
    assign C[3] = G[3] | (P[3] & G[2]) | (P[3] & P[2] & G[1]) | 
            (P[3] & P[2] & P[1] & G[0]);

    //third level
    assign S[0] = P[0];
    assign S[4:1] = P[4:1] ^ C[3:0];   
endmodule
module M_4x4_1 (
    output [7:0] Result,
    input  [3:0] A,
    input  [3:0] B  
);
    wire And_array[3:0][3:0];
    genvar i,j;
    generate
        for (i =0 ;i<4 ;i=i+1 ) begin
            for ( j=0 ;j<4 ;j=j+1 ) begin
                assign And_array[i][j] = A[i] & B[j];
            end
        end
    endgenerate
    assign Result[0] = And_array[0][0];
    //Stage 1 Wallace Tree
    wire [3:0]Sum_1;
    wire [4:0]Carry_1;
    Half_Adder Ha_M4_10(.Sum(Result[1]),
                        .Cout(Carry_1[0]),
                        .A(And_array[1][0]),
                        .B(And_array[0][1]));
    Full_Adder Fa_M4_10(.Sum(Sum_1[0]),
                        .Cout(Carry_1[1]),
                        .A(And_array[2][0]),
                        .B(And_array[1][1]),
                        .C(And_array[0][2]));
    Full_Adder Fa_M4_11(.Sum(Sum_1[1]),
                        .Cout(Carry_1[2]),
                        .A(And_array[3][0]),
                        .B(And_array[2][1]),
                        .C(And_array[1][2]));
    Full_Adder Fa_M4_12(.Sum(Sum_1[2]),
                        .Cout(Carry_1[3]),
                        .A(And_array[3][1]),
                        .B(And_array[2][2]),
                        .C(And_array[1][3]));

    Half_Adder Ha_M4_11(.Sum(Sum_1[3]),
                        .Cout(Carry_1[4]),
                        .A(And_array[3][2]),
                        .B(And_array[2][3]));

    //Stage 2 Wallace Tree
    wire [3:0]Sum_2;
    wire [4:0]Carry_2;
    Half_Adder Ha_M4_20(.Sum(Result[2]),
                        .Cout(Carry_2[0]),
                        .A(Sum_1[0]),
                        .B(Carry_1[0]));
    
    Full_Adder Fa_M4_20 (.Sum(Sum_2[0]),
                        .Cout(Carry_2[1]),
                        .A(Sum_1[1]),
                        .B(Carry_1[1]),
                        .C(And_array[0][3]));
    
    Half_Adder Ha_M4_21 (.Sum(Sum_2[1]),
                        .Cout(Carry_2[2]),
                        .A(Sum_1[2]),
                        .B(Carry_1[2]));

    Half_Adder Ha_M4_22 (.Sum(Sum_2[2]),
                        .Cout(Carry_2[3]),
                        .A(Sum_1[3]),
                        .B(Carry_1[3]));

    Half_Adder Ha_M4_23 (.Sum(Sum_2[3]),
                        .Cout(Carry_2[4]),
                        .A(And_array[3][3]),
                        .B(Carry_1[4]));

    //Carry Look ahead Adder Stage
    M4_Carry_Look_Ahead_Adder CLA_4_0(.S(Result[7:3]),.A(Carry_2),.B(Sum_2));

endmodule

module M_4x4_2 (
    output [7:0] Result,
    input  [3:0] A,
    input  [3:0] B,
    input  Sign  
);
    wire [3:0][3:0]And_array;
    genvar i,j;
    generate
        for (i =0 ;i<3 ;i=i+1 ) begin
            for ( j=0 ;j<4 ;j=j+1 ) begin
                assign And_array[i][j] = A[i] & B[j];
            end
        end
    endgenerate
    generate
        for(i=0;i<4;i=i+1) begin
            assign And_array[3][i]= Sign ^ (A[3] & B[i]);
        end
    endgenerate
    assign Result[0] = And_array[0][0];
    //Stage 1 Wallace Tree
    wire [3:0]Sum_1;
    wire [4:0]Carry_1;
    Half_Adder Ha_M4_10(.Sum(Result[1]),
                        .Cout(Carry_1[0]),
                        .A(And_array[1][0]),
                        .B(And_array[0][1]));
    Full_Adder Fa_M4_10(.Sum(Sum_1[0]),
                        .Cout(Carry_1[1]),
                        .A(And_array[2][0]),
                        .B(And_array[1][1]),
                        .C(And_array[0][2]));
    Full_Adder Fa_M4_11(.Sum(Sum_1[1]),
                        .Cout(Carry_1[2]),
                        .A(And_array[3][0]),
                        .B(And_array[2][1]),
                        .C(And_array[1][2]));
    Full_Adder Fa_M4_12(.Sum(Sum_1[2]),
                        .Cout(Carry_1[3]),
                        .A(And_array[3][1]),
                        .B(And_array[2][2]),
                        .C(And_array[1][3]));

    Half_Adder Ha_M4_11(.Sum(Sum_1[3]),
                        .Cout(Carry_1[4]),
                        .A(And_array[3][2]),
                        .B(And_array[2][3]));

    //Stage 2 Wallace Tree
    wire [3:0]Sum_2;
    wire [4:0]Carry_2;
    Half_Adder Ha_M4_20(.Sum(Result[2]),
                        .Cout(Carry_2[0]),
                        .A(Sum_1[0]),
                        .B(Carry_1[0]));
    
    Full_Adder Fa_M4_20 (.Sum(Sum_2[0]),
                        .Cout(Carry_2[1]),
                        .A(Sum_1[1]),
                        .B(Carry_1[1]),
                        .C(And_array[0][3]));
    
    Half_Adder Ha_M4_21 (.Sum(Sum_2[1]),
                        .Cout(Carry_2[2]),
                        .A(Sum_1[2]),
                        .B(Carry_1[2]));

    Half_Adder Ha_M4_22 (.Sum(Sum_2[2]),
                        .Cout(Carry_2[3]),
                        .A(Sum_1[3]),
                        .B(Carry_1[3]));

    Half_Adder Ha_M4_23 (.Sum(Sum_2[3]),
                        .Cout(Carry_2[4]),
                        .A(And_array[3][3]),
                        .B(Carry_1[4]));

    //Carry Look ahead Adder Stage
    M4_Carry_Look_Ahead_Adder CLA_4_1(.S(Result[7:3]),.A(Carry_2),.B(Sum_2));

endmodule


module M_4x4_3 (
    output [7:0]Result,
    input  [3:0] A,
    input  [3:0] B,
    input  Sign

);
    genvar  i,j;
    wire [3:0][3:0]And_array;

    //And Array 
    generate
        for (i=0 ; i<4 ; i=i+1)
    begin
        for (j=0; j< 3; j=j+1) begin
            assign And_array[i][j] = A[i]&B[j];
        end
    end
    endgenerate
    assign Result[0] = And_array[0][0];

    generate
        for(i=0;i<4;i=i+1) begin
            assign And_array[i][3]= (Sign ^ A[i]) & B[3];
        end
    endgenerate


    //Stage 1 Of Wallace Tree
    wire [5:0]Carry_1;
    wire [4:0]Sum_1;
    Half_Adder Ha_10(.Sum(Result[1]),
                    .Cout(Carry_1[0]),
                    .A(And_array[1][0]),
                    .B(And_array[0][1]));

    Full_Adder Fa_10 (.Sum(Sum_1[0]),
                    .Cout(Carry_1[1]),
                    .A(And_array[2][0]),
                    .B(And_array[1][1]),
                    .C(And_array[0][2]));
    Full_Adder  Fa_11 (.Sum(Sum_1[1]),
                    .Cout(Carry_1[2]),
                    .A(And_array[3][0]),
                    .B(And_array[2][1]),
                    .C(Sign));
    wire Complement;
    assign Complement = B[3] & Sign;
    Full_Adder  Fa_12 (.Sum(Sum_1[2]),
                    .Cout(Carry_1[3]),
                    .A(And_array[1][2]),
                    .B(And_array[0][3]),
                    .C(Complement));

    Full_Adder  Fa_13 (.Sum(Sum_1[3]),
                    .Cout(Carry_1[4]),
                    .A(And_array[3][1]),
                    .B(And_array[2][2]),
                    .C(And_array[1][3]));

    Half_Adder Ha_11 (.Sum(Sum_1[4]),
                    .Cout(Carry_1[5]),
                    .A(And_array[3][2]),
                    .B(And_array[2][3]));
    
    //Stage 2 Of Wallace Tree
    wire [4:0]Carry_2;wire [3:0]Sum_2;
    Half_Adder Ha_20(.Sum(Result[2]),
                    .Cout(Carry_2[0]),
                    .A(Carry_1[0]),
                    .B(Sum_1[0]));
            
    Full_Adder Fa_20(.Sum(Sum_2[0]),
                    .Cout(Carry_2[1]),
                    .A(Carry_1[1]),
                    .B(Sum_1[1]),
                    .C(Sum_1[2]));
    Full_Adder Fa_21(.Sum(Sum_2[1]),
                    .Cout(Carry_2[2]),
                    .A(Carry_1[2]),
                    .B(Carry_1[3]),
                    .C(Sum_1[3]));
    Half_Adder Ha_21(.Sum(Sum_2[2]),
                    .Cout(Carry_2[3]),
                    .A(Carry_1[4]),
                    .B(Sum_1[4]));
    Half_Adder Ha_22(.Sum(Sum_2[3]),
                    .Cout(Carry_2[4]),
                    .A(Carry_1[5]),
                    .B(And_array[3][3]));

    //Carry look ahead Adder Stage

    M4_Carry_Look_Ahead_Adder CLA_4_2(.S(Result[7:3]),.A(Carry_2),.B(Sum_2));



endmodule


module M_4x4_4 (
    output [7:0] Result,
    input  [3:0] A,
    input  [3:0] B,
    input  Sign  
);
    genvar  i,j;
    wire [3:0][3:0]And_array;

    //And Array 
    generate
        for (i=0 ; i<3 ; i=i+1)
    begin
        for (j=0; j< 3; j=j+1) begin
            assign And_array[i][j] = A[i]&B[j];
        end
    end
    endgenerate
    assign Result[0] = And_array[0][0];
    assign And_array[3][3]= B[3] ? A[3] : Sign;

    generate
        for(i=0;i<3;i=i+1) begin
            assign And_array[i][3]= (Sign ^ A[i]) & B[3];
        end
    endgenerate

    generate
        for(j=0;j<3;j=j+1) begin
            assign And_array[3][j]= Sign ^ (A[3] & B[j]);
        end
    endgenerate
    //Stage 1 Wallace Tree
    wire [3:0]Sum_1;
    wire [4:0]Carry_1;
    Half_Adder Ha_M4_10(.Sum(Result[1]),
                        .Cout(Carry_1[0]),
                        .A(And_array[1][0]),
                        .B(And_array[0][1]));
    Full_Adder Fa_M4_10(.Sum(Sum_1[0]),
                        .Cout(Carry_1[1]),
                        .A(And_array[2][0]),
                        .B(And_array[1][1]),
                        .C(And_array[0][2]));
    Full_Adder Fa_M4_11(.Sum(Sum_1[1]),
                        .Cout(Carry_1[2]),
                        .A(And_array[3][0]),
                        .B(And_array[2][1]),
                        .C(And_array[1][2]));
    Full_Adder Fa_M4_12(.Sum(Sum_1[2]),
                        .Cout(Carry_1[3]),
                        .A(And_array[3][1]),
                        .B(And_array[2][2]),
                        .C(And_array[1][3]));

    Half_Adder Ha_M4_11(.Sum(Sum_1[3]),
                        .Cout(Carry_1[4]),
                        .A(And_array[3][2]),
                        .B(And_array[2][3]));

    //Stage 2 Wallace Tree
    wire [3:0]Sum_2;
    wire [4:0]Carry_2;
    Half_Adder Ha_M4_20(.Sum(Result[2]),
                        .Cout(Carry_2[0]),
                        .A(Sum_1[0]),
                        .B(Carry_1[0]));
    
    Full_Adder Fa_M4_20 (.Sum(Sum_2[0]),
                        .Cout(Carry_2[1]),
                        .A(Sum_1[1]),
                        .B(Carry_1[1]),
                        .C(And_array[0][3]));
    
    Half_Adder Ha_M4_21 (.Sum(Sum_2[1]),
                        .Cout(Carry_2[2]),
                        .A(Sum_1[2]),
                        .B(Carry_1[2]));

    Half_Adder Ha_M4_22 (.Sum(Sum_2[2]),
                        .Cout(Carry_2[3]),
                        .A(Sum_1[3]),
                        .B(Carry_1[3]));

    Half_Adder Ha_M4_23 (.Sum(Sum_2[3]),
                        .Cout(Carry_2[4]),
                        .A(And_array[3][3]),
                        .B(Carry_1[4]));

    //Carry Look ahead Adder Stage
    wire [4:0]Sum_Sign;
    assign Sum_Sign = {Sign,Sum_2};
    Carry_Look_Ahead_Adder CLA_4_3(.A(Sum_Sign),.B(Carry_2),.S(Result[7:3]));

endmodule

module Multiplier_8x8 (
    output [15:0] Result,
    input  [7:0] In_1,
    input  [7:0] In_2,
    input  Sign 
);
    wire [3:0][7:0]Partial_Product;
    M_4x4_2 PP_1(.A(In_1[7:4]),.B(In_2[3:0]),.Sign(Sign),.Result(Partial_Product[1][7:0]));
    M_4x4_3 PP_2(.A(In_1[3:0]),.B(In_2[7:4]),.Sign(Sign),.Result(Partial_Product[2][7:0]));
    M_4x4_4 PP_3(.A(In_1[7:4]),.B(In_2[7:4]),.Sign(Sign),.Result(Partial_Product[3][7:0])); 
endmodule

verilog/Adder.v
module Half_Adder (
    output Sum,
    output Cout,
    input  A,
    input  B    
);
    assign Sum = A ^ B;
    assign Cout = A & B;
endmodule

module Full_Adder (
    output Sum,
    output Cout,
    input  A,
    input  B,
    input  C   
);
    wire xor_ab,and_ab;
    assign xor_ab = A ^ B;
    assign Sum = xor_ab ^ C;
    assign and_ab = A & B;
    assign Cout = (xor_ab & C) | and_ab;
endmodule

test_bench/Multiplier_8x8_tb.v
`timescale 1ns / 1ns
`include "verilog/Multiplier_8x8.v"
module Multiplier_8x8_tb ();
    
    reg [7:0] In_1,In_2;
    reg Sign;
    wire [15:0]Result_1;
    Multiplier_8x8 DUT(.Result(Result_1),
                       .In_1(In_1),
                       .In_2(In_2),
                       .Sign(Sign));
    // reg [3:0] In_1,In_2;
    // reg Sign;
    // wire [7:0]Result_1;
    // M_4x4_2 DUT(.Result(Result_1),
    //                    .A(In_1),
    //                    .B(In_2),
    //                    .Sign(Sign));
    initial begin
        $dumpfile("vcd/Multiplier_8x8_tb.vcd");
        $dumpvars(1,DUT);
        Sign = 1;
        for ( integer i=0;i<20 ;i=i+1 ) begin
            In_1 = $urandom_range(0, 15);
            In_2 = $urandom_range(0, 15); 
            #20; 
        end
        Sign = 0;
        for ( integer i=0;i<20 ;i=i+1 ) begin
            In_1 = $urandom_range(0, 15);
            In_2 = $urandom_range(0, 15); 
            #20; 
        end
        $finish();
    end

endmodule

vcd/Multiplier_8x8_tb.vcd
$date
	Sat Sep 14 15:40:22 2024
$end
$version
	Icarus Verilog
$end
$timescale
	1ns
$end
$scope module Multiplier_8x8_tb $end
$scope module DUT $end
$var wire 8 ! In_1 [7:0] $end
$var wire 8 " In_2 [7:0] $end
$var wire 16 # Result [15:0] $end
$var wire 1 $ Sign $end
$var wire 32 % Partial_Product [31:0] $end
$upscope $end
$upscope $end
$enddefinitions $end
$comment Show the parameter values. $end
$dumpall
$end
#0
$dumpvars
b11111000000010000111100000100100 %
1$
bz #
b100 "
b1001 !
$end
#20
b11111000000010000111100000000000 %
b11 "
b0 !
#40
b11111000000010000111100001100000 %
b1100 "
b1000 !
#60
b11111000000010000111100000000000 %
b0 "
b11 !
#80
b11111000000010000111100001000000 %
b1000 "
b1000 !
#100
b11111000000010000111100001100011 %
b1001 "
b1011 !
#120
b11111000000010000111100010110100 %
b1100 "
b1111 !
#140
b11111000000010000111100001011010 %
b110 "
#160
b11111000000010000111100000011110 %
b101 "
b110 !
#180
b11111000000010000111100000101101 %
b11 "
b1111 !
#200
b11111000000010000111100000000000 %
b1100 "
b0 !
#220
b11111000000010000111100001011010 %
b110 "
b1111 !
#240
b11111000000010000111100000101010 %
b111 !
#260
b11111000000010000111100000110010 %
b101 "
b1010 !
#280
b11111000000010000111100000000011 %
b11 "
b1 !
#300
b11111000000010000111100000011000 %
b1000 "
b11 !
#320
b11111000000010000111100000100100 %
b1001 "
b100 !
#340
b11111000000010000111100000110100 %
b100 "
b1101 !
#360
b11111000000010000111100000000000 %
b0 "
b100 !
#380
b10 "
b0 !
#400
b1000010 %
b110 "
b1011 !
0$
#420
b0 %
b101 "
b0 !
#440
b110000 %
b110 "
b1000 !
#460
b1001000 %
b1000 "
b1001 !
#480
b110 %
b1 "
b110 !
#500
b10110100 %
b1100 "
b1111 !
#520
b111100 %
b110 "
b1010 !
#540
b101100 %
b100 "
b1011 !
#560
b11000011 %
b1101 "
b1111 !
#580
b10110110 %
b1110 !
#600
b101101 %
b1001 "
b101 !
#620
b0 %
b11 "
b0 !
#640
b1111000 %
b1010 "
b1100 !
#660
b1001 %
b1001 "
b1 !
#680
b11000 %
b1000 "
b11 !
#700
b11010010 %
b1110 "
b1111 !
#720
b1101110 %
b1010 "
b1011 !
#740
b10010000 %
b1100 "
b1100 !
#760
b1001011 %
b101 "
b1111 !
#780
b1000 %
b10 "
b100 !
