verilog/Look_Ahead_Adder.v
`timescale 1ns / 1ns
module Look_Ahead_Adder(A,B,S,Cout,Cin);
input [3:0] A,B;
output [3:0] S;
output Cout;
input Cin;
wire P0,P1,P2,P3;
wire G0,G1,G2,G3;
wire C1,C2,C3,C4;
ha X1(A[0],B[0],P0,G0);
ha X2(A[1],B[1],P1,G1);
ha X3(A[2],B[2],P2,G2);
ha X4(A[3],B[3],P3,G3);
assign C1 = G0 | P0&Cin;
assign C2 = G1 | P1&G0 | P1&P0&Cin;
assign C3 = G2 | P2&G1 | P2&P1&G0 | P2&P1&P0&Cin;
assign C4 = G3 | P3&G2 | P3&P2&G1 | P3&P2&P1&P0&Cin;
assign S[0] = P0 ^ Cin;
assign S[1] = P1 ^ C1;
assign S[2] = P2 ^ C2;
assign S[3] = P3 ^ C3;
assign Cout = C4;
endmodule

module Look_Ahead_Adder_No_Cin(A,B,S,Cout);
input [3:0] A,B;
output [3:0] S;
output Cout;
wire P0,P1,P2,P3;
wire G0,G1,G2,G3;
wire C1,C2,C3,C4;
ha X1(A[0],B[0],P0,G0);
ha X2(A[1],B[1],P1,G1);
ha X3(A[2],B[2],P2,G2);
ha X4(A[3],B[3],P3,G3);
assign C1 = G0 ;
assign C2 = G1 | P1&G0 ;
assign C3 = G2 | P2&G1 | P2&P1&G0 ;
assign C4 = G3 | P3&G2 | P3&P2&G1 ;
assign S[0] = P0 ;
assign S[1] = P1 ^ C1;
assign S[2] = P2 ^ C2;
assign S[3] = P3 ^ C3;
assign Cout = C4;
endmodule

module ha(
  input a,b,
  output sum,co
    );
assign sum = a^b;
assign co = a&b;
endmodule

module Increment (
  input  [2:0] A,
  input  B,
  output [2:0] S  
);
  wire P,G;
  assign P = A[0] ^ B;
  assign G = A[0] & B;
  wire C1,C2,C3;
  assign C1 = G ;
  assign C2 = A[1]&G;
  assign C3 = A[2]&A[1]&G ;
  assign S[0] = P ;
  assign S[1] = A[1] ^ C1;
  assign S[2] = A[2]^ C2;

endmodule

verilog/Multiplier_8x8.v
`include "verilog/Adder.v"
`include "verilog/Look_Ahead_Adder.v"
module Carry_Look_Ahead_Adder
        (   input [4:0] A,B,
            output [4:0] S
            );
            
    wire [4:0] P;
    wire [3:0] G;
    wire [3:0] C;   
    
        //first level
    assign P = A ^ B;
    assign G = A[3:0] & B[3:0];

    //second level
    // assign C[0] = cin;
    assign C[0] = G[0];
    assign C[1] = G[1] | (P[1] & G[0]) ;
    assign C[2] = G[2] | (P[2] & G[1]) | (P[2] & P[1] & G[0]);
    assign C[3] = G[3] | (P[3] & G[2]) | (P[3] & P[2] & G[1]) | 
            (P[3] & P[2] & P[1] & G[0]);

    //third level
    assign S[0] = P[0];
    assign S[4:1] = P[4:1] ^ C[3:0];

endmodule
module M4_Carry_Look_Ahead_Adder (
    output [4:0]  S,
    input  [4:0] A,
    input  [3:0] B
    );
    wire [4:0] P;
    wire [3:0] G;
    wire [3:0] C;   
    
    //first level
    assign P[4] =A[4];
    assign P[3:0] = A[3:0] ^ B;
    assign G = A[3:0] & B;

    //second level
    assign C[0] = G[0];
    assign C[1] = G[1] | (P[1] & G[0]) ;
    assign C[2] = G[2] | (P[2] & G[1]) | (P[2] & P[1] & G[0]);
    assign C[3] = G[3] | (P[3] & G[2]) | (P[3] & P[2] & G[1]) | 
            (P[3] & P[2] & P[1] & G[0]);

    //third level
    assign S[0] = P[0];
    assign S[4:1] = P[4:1] ^ C[3:0];   
endmodule
module M_4x4_1 (
    output [7:0] Result,
    input  [3:0] A,
    input  [3:0] B  
);
    wire And_array[3:0][3:0];
    genvar i,j;
    generate
        for (i =0 ;i<4 ;i=i+1 ) begin
            for ( j=0 ;j<4 ;j=j+1 ) begin
                assign And_array[i][j] = A[i] & B[j];
            end
        end
    endgenerate
    assign Result[0] = And_array[0][0];
    //Stage 1 Wallace Tree
    wire [3:0]Sum_1;
    wire [4:0]Carry_1;
    Half_Adder Ha_M4_10(.Sum(Result[1]),
                        .Cout(Carry_1[0]),
                        .A(And_array[1][0]),
                        .B(And_array[0][1]));
    Full_Adder Fa_M4_10(.Sum(Sum_1[0]),
                        .Cout(Carry_1[1]),
                        .A(And_array[2][0]),
                        .B(And_array[1][1]),
                        .C(And_array[0][2]));
    Full_Adder Fa_M4_11(.Sum(Sum_1[1]),
                        .Cout(Carry_1[2]),
                        .A(And_array[3][0]),
                        .B(And_array[2][1]),
                        .C(And_array[1][2]));
    Full_Adder Fa_M4_12(.Sum(Sum_1[2]),
                        .Cout(Carry_1[3]),
                        .A(And_array[3][1]),
                        .B(And_array[2][2]),
                        .C(And_array[1][3]));

    Half_Adder Ha_M4_11(.Sum(Sum_1[3]),
                        .Cout(Carry_1[4]),
                        .A(And_array[3][2]),
                        .B(And_array[2][3]));

    //Stage 2 Wallace Tree
    wire [3:0]Sum_2;
    wire [4:0]Carry_2;
    Half_Adder Ha_M4_20(.Sum(Result[2]),
                        .Cout(Carry_2[0]),
                        .A(Sum_1[0]),
                        .B(Carry_1[0]));
    
    Full_Adder Fa_M4_20 (.Sum(Sum_2[0]),
                        .Cout(Carry_2[1]),
                        .A(Sum_1[1]),
                        .B(Carry_1[1]),
                        .C(And_array[0][3]));
    
    Half_Adder Ha_M4_21 (.Sum(Sum_2[1]),
                        .Cout(Carry_2[2]),
                        .A(Sum_1[2]),
                        .B(Carry_1[2]));

    Half_Adder Ha_M4_22 (.Sum(Sum_2[2]),
                        .Cout(Carry_2[3]),
                        .A(Sum_1[3]),
                        .B(Carry_1[3]));

    Half_Adder Ha_M4_23 (.Sum(Sum_2[3]),
                        .Cout(Carry_2[4]),
                        .A(And_array[3][3]),
                        .B(Carry_1[4]));

    //Carry Look ahead Adder Stage
    M4_Carry_Look_Ahead_Adder CLA_4_0(.S(Result[7:3]),.A(Carry_2),.B(Sum_2));

endmodule

module M_4x4_2 (
    output [7:0] Result,
    input  [3:0] A,
    input  [3:0] B,
    input  Sign  
);
    wire [3:0][3:0]And_array;
    genvar i,j;
    generate
        for (i =0 ;i<3 ;i=i+1 ) begin
            for ( j=0 ;j<4 ;j=j+1 ) begin
                assign And_array[i][j] = A[i] & B[j];
            end
        end
    endgenerate
    generate
        for(i=0;i<4;i=i+1) begin
            assign And_array[3][i]= Sign ^ (A[3] & B[i]);
        end
    endgenerate
    assign Result[0] = And_array[0][0];
    //Stage 1 Wallace Tree
    wire [3:0]Sum_1;
    wire [4:0]Carry_1;
    Half_Adder Ha_M4_10(.Sum(Result[1]),
                        .Cout(Carry_1[0]),
                        .A(And_array[1][0]),
                        .B(And_array[0][1]));
    Full_Adder Fa_M4_10(.Sum(Sum_1[0]),
                        .Cout(Carry_1[1]),
                        .A(And_array[2][0]),
                        .B(And_array[1][1]),
                        .C(And_array[0][2]));
    Full_Adder Fa_M4_11(.Sum(Sum_1[1]),
                        .Cout(Carry_1[2]),
                        .A(And_array[3][0]),
                        .B(And_array[2][1]),
                        .C(And_array[1][2]));
    Full_Adder Fa_M4_12(.Sum(Sum_1[2]),
                        .Cout(Carry_1[3]),
                        .A(And_array[3][1]),
                        .B(And_array[2][2]),
                        .C(And_array[1][3]));

    Half_Adder Ha_M4_11(.Sum(Sum_1[3]),
                        .Cout(Carry_1[4]),
                        .A(And_array[3][2]),
                        .B(And_array[2][3]));

    //Stage 2 Wallace Tree
    wire [3:0]Sum_2;
    wire [4:0]Carry_2;
    Half_Adder Ha_M4_20(.Sum(Result[2]),
                        .Cout(Carry_2[0]),
                        .A(Sum_1[0]),
                        .B(Carry_1[0]));
    
    Full_Adder Fa_M4_20 (.Sum(Sum_2[0]),
                        .Cout(Carry_2[1]),
                        .A(Sum_1[1]),
                        .B(Carry_1[1]),
                        .C(And_array[0][3]));
    
    Half_Adder Ha_M4_21 (.Sum(Sum_2[1]),
                        .Cout(Carry_2[2]),
                        .A(Sum_1[2]),
                        .B(Carry_1[2]));

    Half_Adder Ha_M4_22 (.Sum(Sum_2[2]),
                        .Cout(Carry_2[3]),
                        .A(Sum_1[3]),
                        .B(Carry_1[3]));

    Half_Adder Ha_M4_23 (.Sum(Sum_2[3]),
                        .Cout(Carry_2[4]),
                        .A(And_array[3][3]),
                        .B(Carry_1[4]));

    //Carry Look ahead Adder Stage
    M4_Carry_Look_Ahead_Adder CLA_4_1(.S(Result[7:3]),.A(Carry_2),.B(Sum_2));

endmodule


module M_4x4_3 (
    output [7:0]Result,
    input  [3:0] A,
    input  [3:0] B,
    input  Sign

);
    genvar  i,j;
    wire [3:0][3:0]And_array;

    //And Array 
    generate
        for (i=0 ; i<4 ; i=i+1)
    begin
        for (j=0; j< 3; j=j+1) begin
            assign And_array[i][j] = A[i]&B[j];
        end
    end
    endgenerate
    assign Result[0] = And_array[0][0];

    generate
        for(i=0;i<4;i=i+1) begin
            assign And_array[i][3]= (Sign ^ A[i]) & B[3];
        end
    endgenerate


    //Stage 1 Of Wallace Tree
    wire [5:0]Carry_1;
    wire [4:0]Sum_1;
    Half_Adder Ha_10(.Sum(Result[1]),
                    .Cout(Carry_1[0]),
                    .A(And_array[1][0]),
                    .B(And_array[0][1]));

    Full_Adder Fa_10 (.Sum(Sum_1[0]),
                    .Cout(Carry_1[1]),
                    .A(And_array[2][0]),
                    .B(And_array[1][1]),
                    .C(And_array[0][2]));
    Full_Adder  Fa_11 (.Sum(Sum_1[1]),
                    .Cout(Carry_1[2]),
                    .A(And_array[3][0]),
                    .B(And_array[2][1]),
                    .C(Sign));
    wire Complement;
    assign Complement = B[3] & Sign;
    Full_Adder  Fa_12 (.Sum(Sum_1[2]),
                    .Cout(Carry_1[3]),
                    .A(And_array[1][2]),
                    .B(And_array[0][3]),
                    .C(Complement));

    Full_Adder  Fa_13 (.Sum(Sum_1[3]),
                    .Cout(Carry_1[4]),
                    .A(And_array[3][1]),
                    .B(And_array[2][2]),
                    .C(And_array[1][3]));

    Half_Adder Ha_11 (.Sum(Sum_1[4]),
                    .Cout(Carry_1[5]),
                    .A(And_array[3][2]),
                    .B(And_array[2][3]));
    
    //Stage 2 Of Wallace Tree
    wire [4:0]Carry_2;wire [3:0]Sum_2;
    Half_Adder Ha_20(.Sum(Result[2]),
                    .Cout(Carry_2[0]),
                    .A(Carry_1[0]),
                    .B(Sum_1[0]));
            
    Full_Adder Fa_20(.Sum(Sum_2[0]),
                    .Cout(Carry_2[1]),
                    .A(Carry_1[1]),
                    .B(Sum_1[1]),
                    .C(Sum_1[2]));
    Full_Adder Fa_21(.Sum(Sum_2[1]),
                    .Cout(Carry_2[2]),
                    .A(Carry_1[2]),
                    .B(Carry_1[3]),
                    .C(Sum_1[3]));
    Half_Adder Ha_21(.Sum(Sum_2[2]),
                    .Cout(Carry_2[3]),
                    .A(Carry_1[4]),
                    .B(Sum_1[4]));
    Half_Adder Ha_22(.Sum(Sum_2[3]),
                    .Cout(Carry_2[4]),
                    .A(Carry_1[5]),
                    .B(And_array[3][3]));

    //Carry look ahead Adder Stage

    M4_Carry_Look_Ahead_Adder CLA_4_2(.S(Result[7:3]),.A(Carry_2),.B(Sum_2));



endmodule


module M_4x4_4 (
    output [7:0] Result,
    input  [3:0] A,
    input  [3:0] B,
    input  Sign ,
    input Mode
);
        genvar  i,j;
    wire And_array[3:0][3:0];

    //And Array 
    generate
        for (i=0 ; i<3 ; i=i+1)
    begin
        for (j=0; j< 3; j=j+1) begin
            assign And_array[i][j] = A[i]&B[j];
        end
    end
    endgenerate
    assign Result[0] = And_array[0][0];
    assign And_array[3][3]= B[3] ? A[3] : Sign;

    generate
        for(i=0;i<3;i=i+1) begin
            assign And_array[i][3]= (Sign ^ A[i]) & B[3];
        end
    endgenerate

    generate
        for(j=0;j<3;j=j+1) begin
            assign And_array[3][j]= Sign ^ (A[3] & B[j]);
        end
    endgenerate

    //Stage 1 Of Wallace Tree
    wire [5:0]Carry_1;
    wire [4:0]Sum_1;
    wire Mode_sign;
    assign Mode_sign = Mode & Sign;
    Half_Adder Ha_10(.Sum(Result[1]),
                    .Cout(Carry_1[0]),
                    .A(And_array[1][0]),
                    .B(And_array[0][1]));

    Full_Adder Fa_10 (.Sum(Sum_1[0]),
                    .Cout(Carry_1[1]),
                    .A(And_array[2][0]),
                    .B(And_array[1][1]),
                    .C(And_array[0][2]));
    Full_Adder  Fa_11 (.Sum(Sum_1[1]),
                    .Cout(Carry_1[2]),
                    .A(And_array[3][0]),
                    .B(And_array[2][1]),
                    .C(Mode_sign));
    wire Complement;
    assign Complement = B[3] & Sign & Mode;
    Full_Adder  Fa_12 (.Sum(Sum_1[2]),
                    .Cout(Carry_1[3]),
                    .A(And_array[1][2]),
                    .B(And_array[0][3]),
                    .C(Complement));

    Full_Adder  Fa_13 (.Sum(Sum_1[3]),
                    .Cout(Carry_1[4]),
                    .A(And_array[3][1]),
                    .B(And_array[2][2]),
                    .C(And_array[1][3]));

    Half_Adder Ha_11 (.Sum(Sum_1[4]),
                    .Cout(Carry_1[5]),
                    .A(And_array[3][2]),
                    .B(And_array[2][3]));
    
    //Stage 2 Of Wallace Tree
    wire [4:0]Carry_2;wire [3:0]Sum_2;
    Half_Adder Ha_20(.Sum(Result[2]),
                    .Cout(Carry_2[0]),
                    .A(Carry_1[0]),
                    .B(Sum_1[0]));
            
    Full_Adder Fa_20(.Sum(Sum_2[0]),
                    .Cout(Carry_2[1]),
                    .A(Carry_1[1]),
                    .B(Sum_1[1]),
                    .C(Sum_1[2]));
    Full_Adder Fa_21(.Sum(Sum_2[1]),
                    .Cout(Carry_2[2]),
                    .A(Carry_1[2]),
                    .B(Carry_1[3]),
                    .C(Sum_1[3]));
    Half_Adder Ha_21(.Sum(Sum_2[2]),
                    .Cout(Carry_2[3]),
                    .A(Carry_1[4]),
                    .B(Sum_1[4]));
    Half_Adder Ha_22(.Sum(Sum_2[3]),
                    .Cout(Carry_2[4]),
                    .A(Carry_1[5]),
                    .B(And_array[3][3]));

    //Carry look ahead Adder Stage

    wire [4:0]Sum_Sign;
    assign Sum_Sign = {Sign,Sum_2};
    Carry_Look_Ahead_Adder CLA(.A(Sum_Sign),.B(Carry_2),.S(Result[7:3]));

endmodule

module Multiplier_8x8 (
    output [15:0] Result,
    input  [7:0] In_1,
    input  [7:0] In_2,
    input  Sign,
    input Mode
);
    wire [3:0][7:0]Partial_Product;
    wire [7:0]Sum_R123; 
    wire [7:0]Cout_R123;
    wire  [1:0]Cout;
    M_4x4_1 PP_0(.A(In_1[3:0]),.B(In_2[3:0]),.Result(Partial_Product[0][7:0]));
    M_4x4_2 PP_1(.A(In_1[7:4]),.B(In_2[3:0]),.Sign(Sign),.Result(Partial_Product[1][7:0]));
    M_4x4_3 PP_2(.A(In_1[3:0]),.B(In_2[7:4]),.Sign(Sign),.Result(Partial_Product[2][7:0]));
    M_4x4_4 PP_3(.A(In_1[7:4]),.B(In_2[7:4]),.Sign(Sign),.Result(Partial_Product[3][7:0]),.Mode(Mode)); 
    assign Result[3:0]=Partial_Product[0][3:0];
    wire [7:0] Partial_Product_Inter = {Partial_Product[3][3:0],Partial_Product[0][7:4]};
    assign Sum_R123 = Partial_Product_Inter  ^ Partial_Product[1] ^ Partial_Product[2];
    assign Cout_R123 = Partial_Product_Inter  & Partial_Product[1] | 
                       Partial_Product_Inter & Partial_Product[2] |
                       Partial_Product[1] & Partial_Product[2] ;

    
    assign Result[4] = Sum_R123[0];
    wire [7:0]Sum_R123_1;
    Look_Ahead_Adder_No_Cin CLA_1(.A(Sum_R123[4:1]),
                                  .B(Cout_R123[3:0]),
                                  .S(Sum_R123_1[3:0]),
                                  .Cout(Cout[0]));

    Look_Ahead_Adder CLA_2(.A(Cout_R123[7:4]),
                           .B({Partial_Product[3][4],Sum_R123[7:5]}),
                           .Cin(Cout[0]),
                           .S(Sum_R123_1[7:4]),
                           .Cout(Cout[1]));

    assign Result[12:5]= Sum_R123_1;

    Increment I0(.A(Partial_Product[3][7:5]),
                  .B(Cout[1]),
                  .S(Result[15:13]));

    
endmodule

verilog/Adder.v
module Half_Adder (
    output Sum,
    output Cout,
    input  A,
    input  B    
);
    assign Sum = A ^ B;
    assign Cout = A & B;
endmodule

module Full_Adder (
    output Sum,
    output Cout,
    input  A,
    input  B,
    input  C   
);
    wire xor_ab,and_ab;
    assign xor_ab = A ^ B;
    assign Sum = xor_ab ^ C;
    assign and_ab = A & B;
    assign Cout = (xor_ab & C) | and_ab;
endmodule

test_bench/Multiplier_8x8_tb.v
`timescale 1ns / 1ns
`include "verilog/Multiplier_8x8.v"
module Multiplier_8x8_tb ();
    reg Mode;
    reg [7:0] In_1,In_2;
    reg Sign;
    wire [15:0]Result_1;
    Multiplier_8x8 DUT(.Result(Result_1),
                       .In_1(In_1),
                       .In_2(In_2),
                       .Sign(Sign),
                       .Mode(Mode));
    // reg [3:0] In_1,In_2;
    // reg Sign;
    // wire [7:0]Result_1;
    // M_4x4_2 DUT(.Result(Result_1),
    //                    .A(In_1),
    //                    .B(In_2),
    //                    .Sign(Sign));
    initial begin
        $dumpfile("vcd/Multiplier_8x8_tb.vcd");
        $dumpvars(1,DUT);
        Mode = 1;
        Sign = 0;
        for ( integer i=0;i<20 ;i=i+1 ) begin
            In_1 = $urandom_range(0, 255);
            In_2 = $urandom_range(0, 255); 
            #20; 
        end
        Sign = 0;
        for ( integer i=0;i<20 ;i=i+1 ) begin
            In_1 = $urandom_range(0, 15);
            In_2 = $urandom_range(0, 15); 
            #20; 
        end
        $finish();
    end

endmodule

vcd/Multiplier_8x8_tb.vcd
$date
	Wed Oct  2 21:50:19 2024
$end
$version
	Icarus Verilog
$end
$timescale
	1ns
$end
$scope module Multiplier_8x8_tb $end
$scope module DUT $end
$var wire 8 ! Cout_R123 [7:0] $end
$var wire 8 " In_1 [7:0] $end
$var wire 8 # In_2 [7:0] $end
$var wire 1 $ Mode $end
$var wire 1 % Sign $end
$var wire 8 & Sum_R123 [7:0] $end
$var wire 8 ' Sum_R123_1 [7:0] $end
$var wire 16 ( Result [15:0] $end
$var wire 8 ) Partial_Product_Inter [7:0] $end
$var wire 32 * Partial_Product [31:0] $end
$var wire 2 + Cout [1:0] $end
$upscope $end
$upscope $end
$enddefinitions $end
$comment Show the parameter values. $end
$dumpall
$end
#0
$dumpvars
b0 +
b100100000010000000000000000000 *
b1000000 )
b10010010000000 (
b100100 '
b1001000 &
0%
1$
b1000000 #
b10010010 "
b0 !
$end
#20
b110 '
b1100 &
b11000100 (
b0 )
b11000000000000000100 *
b110001 #
b100 "
#40
b111101 '
b0 !
b10 )
b1111010 &
b110011110100100 (
b1100000010010000011000000100100 *
b11000110 #
b10000110 "
#60
b0 +
b1 )
b1110 '
b1 !
b11010 &
b111000010 (
b1101100010010 *
b1001 #
b110010 "
#80
b11000 '
b0 )
b0 !
b110000 &
b100001100000000 (
b1000000000000000011000000000000 *
b10000110 #
b10000000 "
#100
b10011011 '
b111011 !
b11000000 &
b111001101101010 (
b111001 )
b1100011011000111001101010011010 *
b10011110 #
b10111011 "
#120
b1 +
b11110010 '
b1001010 !
b1010000 &
b1011111001000100 (
b1000010 )
b10110100010010000101101000100100 *
b11000110 #
b11110110 "
#140
b10 +
b1011 '
b101000 !
b110000101110100 (
b11000111 &
b10100010 )
b1011010010010000010110100100100 *
b1100011 #
b11111100 "
#160
b11 +
b100 '
b1010 !
b11110100 &
b11100000 )
b10000010001010 (
b11110000010100001111000001010 *
b1010101 #
b1100010 "
#180
b0 +
b10111110 '
b11011111000110 (
b10000101 !
b1110010 &
b11010001 )
b101101000001101010010100010110 *
b111011 #
b11110010 "
#200
b0 +
b110111 '
b0 !
b1101111 &
b11011111111 (
b11 )
b11011000000000000111111 *
b11000111 #
b1001 "
#220
b11 +
b100001 '
b100011 !
b110010000101111 (
b11111100 &
b10100011 )
b1011010001101100110100100111111 *
b1100111 #
b11111001 "
#240
b1 +
b1100011 '
b10100000 )
b1000 !
b10110110 &
b10110001101000 (
b101010000110000000111000001000 *
b1100010 #
b1110100 "
#260
b0 +
b1100 !
b11111111 '
b11111111100100 (
b11100110 &
b101100 )
b110010010001101000110011000100 *
b1011110 #
b10101110 "
#280
b0 +
b10001001100 (
b100010 '
b10010 !
b100000 &
b110000 )
b11000100100000001000001100 *
b110010 #
b10110 "
#300
b0 +
b11001011 '
b1000 !
b10000111 &
b10000000 )
b1100101110101 (
b11000000010000000111100000101 *
b10000101 #
b110001 "
#320
b0 !
b100000 '
b1000000 )
b1000000 &
b10010000000000 (
b100100000000000000000000000000 *
b10010000 #
b1000000 "
#340
b0 +
b111 '
b10100 !
b11100110 &
b1000100 )
b10000011100110 (
b110100000101001011011001000110 *
b1001110 #
b11010101 "
#360
b10101 '
b100 !
b100010 &
b110 )
b1010100011 (
b10010001100011 *
b1001 #
b1001011 "
#380
b111 '
b0 !
b1111 &
b11 )
b11110110 (
b11000000000000110110 *
b101001 #
b110 "
#400
b10 '
b100 )
b100 &
b1000010 (
b1000010 *
b110 #
b1011 "
#420
b0 '
b0 &
b0 )
b0 (
b0 *
b101 #
b0 "
#440
b1 '
b110000 (
b11 &
b11 )
b110000 *
b110 #
b1000 "
#460
b10 '
b100 &
b100 )
b1001000 (
b1001000 *
b1000 #
b1001 "
#480
b0 '
b0 &
b0 )
b110 (
b110 *
b1 #
b110 "
#500
b101 '
b1011 &
b1011 )
b10110100 (
b10110100 *
b1100 #
b1111 "
#520
b1 '
b11 &
b11 )
b111100 (
b111100 *
b110 #
b1010 "
#540
b10 &
b10 )
b101100 (
b101100 *
b100 #
b1011 "
#560
b110 '
b1100 &
b1100 )
b11000011 (
b11000011 *
b1101 #
b1111 "
#580
b101 '
b1011 &
b1011 )
b10110110 (
b10110110 *
b1110 "
#600
b1 '
b10 &
b10 )
b101101 (
b101101 *
b1001 #
b101 "
#620
b0 '
b0 &
b0 )
b0 (
b0 *
b11 #
b0 "
#640
b11 '
b1111000 (
b111 &
b111 )
b1111000 *
b1010 #
b1100 "
#660
b0 '
b0 &
b0 )
b1001 (
b1001 *
b1001 #
b1 "
#680
b1 &
b1 )
b11000 (
b11000 *
b1000 #
b11 "
#700
b110 '
b1101 &
b1101 )
b11010010 (
b11010010 *
b1110 #
b1111 "
#720
b11 '
b110 &
b110 )
b1101110 (
b1101110 *
b1010 #
b1011 "
#740
b100 '
b1001 &
b1001 )
b10010000 (
b10010000 *
b1100 #
b1100 "
#760
b10 '
b100 &
b100 )
b1001011 (
b1001011 *
b101 #
b1111 "
#780
b0 '
b0 &
b0 )
b1000 (
b1000 *
b10 #
b100 "
