verilog/Adder.v
module Half_Adder (
    output Sum,
    output Cout,
    input  A,
    input  B    
);
    assign Sum = A ^ B;
    assign Cout = A & B;
endmodule

module Full_Adder (
    output Sum,
    output Cout,
    input  A,
    input  B,
    input  C   
);
    wire xor_ab,and_ab;
    assign xor_ab = A ^ B;
    assign Sum = xor_ab ^ C;
    assign and_ab = A & B;
    assign Cout = (xor_ab & C) | and_ab;
endmodule

verilog/Vedic_2x2.v
`include "Half_Adder.v"
module Vedic_2x2 (
    output [3:0] Result,
    input  [1:0] In_1,
    input  [1:0] In_2  
);
    wire [2:0]temp; wire Sum_1;
    assign Result[0] = In_1[0] & In_2[0];
    assign temp[0] = In_1[1] & In_2[0];
    assign temp[1] = In_1[0] & In_2[1];
    assign temp[2] = In_1[1] & In_2[1];
    Half_Adder H1(.Sum(Result[1]),.Cout(Sum_1),.A(temp[0]),.B(temp[1]));
    Half_Adder H2(.Sum(Result[2]),.Cout(Result[3]),.A(temp[2]),.B(Sum_1));
endmodule

test_bench/Vedic_2x2_tb.v
`timescale 1ns / 1ns
module Vedic_2x2_tb();

     reg [1:0]In_1;reg [1:0]In_2;
     wire [3:0]Result;

     Vedic_2x2 DUI(.In_1(In_1),.In_2(In_2),.Result(Result));

     initial begin
    $dumpfile("vcd/Vedic_2x2_tb.vcd");
    $dumpvars(0, Vedic_2x2_tb);
    for (integer i=0; i<4 ; i++ ) begin
         In_1 = i;
        for (integer j =0 ;j<4 ;j++ ) begin
            In_2 = j;
            #20;
        end
    end 
    $finish();

end
    
endmodule

vcd/Vedic_2x2_tb.vcd
$date
	Sat Sep  7 22:13:46 2024
$end
$version
	Icarus Verilog
$end
$timescale
	1ns
$end
$scope module Vedic_2x2_tb $end
$var wire 4 ! Result [3:0] $end
$var reg 2 " In_1 [1:0] $end
$var reg 2 # In_2 [1:0] $end
$scope module DUI $end
$var wire 2 $ In_1 [1:0] $end
$var wire 2 % In_2 [1:0] $end
$var wire 3 & temp [2:0] $end
$var wire 1 ' Sum_1 $end
$var wire 4 ( Result [3:0] $end
$scope module H1 $end
$var wire 1 ) A $end
$var wire 1 * B $end
$var wire 1 ' Cout $end
$var wire 1 + Sum $end
$upscope $end
$scope module H2 $end
$var wire 1 , A $end
$var wire 1 ' B $end
$var wire 1 - Cout $end
$var wire 1 . Sum $end
$upscope $end
$upscope $end
$scope begin $ivl_for_loop0 $end
$var integer 32 / i [31:0] $end
$scope begin $ivl_for_loop1 $end
$var integer 32 0 j [31:0] $end
$upscope $end
$upscope $end
$upscope $end
$enddefinitions $end
$comment Show the parameter values. $end
$dumpall
$end
#0
$dumpvars
b0 0
b0 /
0.
0-
0,
0+
0*
0)
b0 (
0'
b0 &
b0 %
b0 $
b0 #
b0 "
b0 !
$end
#20
b1 #
b1 %
b1 0
#40
b10 #
b10 %
b10 0
#60
b11 #
b11 %
b11 0
#80
b0 #
b0 %
b1 "
b1 $
b1 /
b0 0
#100
b1 !
b1 (
b1 #
b1 %
b1 0
#120
1+
1*
b10 !
b10 (
b10 &
b10 #
b10 %
b10 0
#140
b11 !
b11 (
b11 #
b11 %
b11 0
#160
0+
0*
b0 !
b0 (
b0 &
b0 #
b0 %
b10 "
b10 $
b10 /
b0 0
#180
b10 !
b10 (
1+
1)
b1 &
b1 #
b1 %
b1 0
#200
0+
b100 !
b100 (
1.
0)
1,
b100 &
b10 #
b10 %
b10 0
#220
b110 !
b110 (
1+
1)
b101 &
b11 #
b11 %
b11 0
#240
0+
b0 !
b0 (
0.
0)
0,
b0 &
b0 #
b0 %
b11 "
b11 $
b11 /
b0 0
#260
1+
1)
b11 !
b11 (
b1 &
b1 #
b1 %
b1 0
#280
1.
0)
1*
1,
b110 !
b110 (
b110 &
b10 #
b10 %
b10 0
#300
0.
1-
0+
1'
1)
b1001 !
b1001 (
b111 &
b11 #
b11 %
b11 0
#320
b100 /
b100 0
